3d_to_image-0.1.2.dist-info/licenses/LICENSE.txt
model_to_image/__init__.py
model_to_image/glb_to_image.py
model_to_image/obj_to_image.py
model_to_image/stl_to_image.py
3d_to_image-0.1.2.dist-info/METADATA
3d_to_image-0.1.2.dist-info/WHEEL
3d_to_image-0.1.2.dist-info/top_level.txt
3d_to_image-0.1.2.dist-info/RECORD
