Metadata-Version: 2.4
Name: 3d-to-image
Version: 0.1.2
Summary: A Python package for converting 3D files to images.
Author-email: Muhammad Ateeq <mr.ateeqazam@gmail.com>
License: CC BY-ND
Keywords: 3D processing,3D to image,computer vision
License-File: LICENSE.txt
Requires-Dist: opencv-python
Requires-Dist: numpy
Requires-Dist: scipy
Requires-Dist: scikit-learn
Requires-Dist: pyrender
Requires-Dist: trimesh
Requires-Dist: matplotlib
Requires-Dist: pyvista
Dynamic: license-file
